nato_opt/__init__.py
nato_opt/fft_helpers.py
nato_opt/filtering.py
nato_opt/optimizer.py
nato_opt/spectral.py
nato_opt/utils.py
nato_opt-0.1.0.dist-info/licenses/LICENSE
nato_opt-0.1.0.dist-info/METADATA
nato_opt-0.1.0.dist-info/WHEEL
nato_opt-0.1.0.dist-info/top_level.txt
nato_opt-0.1.0.dist-info/RECORD
