Metadata-Version: 2.4
Name: nato-opt
Version: 0.1.0
Summary: NATO Optimizer with Fourier Spectral Penalty (FSP) and N-D FFT gradient filtering
Author-email: Malhar Pangarkar <malharpangarkar19@gmail.com>, Atharva Khambete <atharvakhambete1@gmail.com>
Requires-Python: >=3.8
License-File: LICENSE
Requires-Dist: torch
Requires-Dist: numpy
Dynamic: license-file
